setup.py
minica/__init__.py
minica/net.py
minica/tensor.py
minica.egg-info/PKG-INFO
minica.egg-info/SOURCES.txt
minica.egg-info/dependency_links.txt
minica.egg-info/requires.txt
minica.egg-info/top_level.txt
minica/layers/__init__.py
minica/layers/accuracy_layer.py
minica/layers/argmax_layer.py
minica/layers/conv_layer.py
minica/layers/cross_entropy_layer.py
minica/layers/full_layer.py
minica/layers/mean_squared_error_layer.py
minica/layers/pooling_layer.py
minica/layers/relu_layer.py
minica/layers/softmax_cross_entropy_layer.py
minica/layers/softmax_layer.py
minica/optimize/__init__.py
minica/optimize/conv_func.c
minica/optimize/pooling_func.c
minica/solvers/__init__.py
minica/solvers/sgd_solver.py
minica/util/__init__.py
minica/util/gradient_checker.py