Metadata-Version: 1.1
Name: minica
Version: 0.0.1
Summary: Yet another neural net library. :)
Home-page: UNKNOWN
Author: Lei He
Author-email: heleifz@126.com
License: MIT
Keywords: neural net machine learning
Platform: UNKNOWN
Classifier: Development Status :: 3 - Alpha
Classifier: Topic :: Scientific/Engineering :: Artificial Intelligence
Classifier: License :: OSI Approved :: MIT License
